{"is_source_file": true, "format": ".ts", "description": "middleware.ts - small file (2552 bytes)", "external_files": [], "external_methods": [], "published": [], "classes": [], "methods": [], "calls": [], "search-terms": ["middleware.ts", ".ts", "version_keerthana"], "state": 2, "ctags": [], "filename": "version_keerthana/middleware.ts", "format-version": 4, "code-base-name": "https://github.com/rossiniheyyou-cyber/dt310feb.git:kavia-main-1431", "knowledge_revision": 87, "git_revision": "8b4f16291bb8e796f816193d02e2adf7948a512c", "revision_history": [{"87": "8b4f16291bb8e796f816193d02e2adf7948a512c"}]}